{
    "version": "https://jsonfeed.org/version/1",
    "title": "Tea Blog",
    "home_page_url": "https://clark-cui.top/",
    "feed_url": "https://clark-cui.top/feed.json",
    "description": "Tea Blog' Blog",
    "icon": "https://clark-cui.top/horse.svg",
    "author": {
        "name": "Tea Blog",
        "url": "https://clark-cui.top"
    },
    "items": [
        {
            "content_html": "<h1>作品</h1>\n<p><a href=\"https://github.com/tea-blog/auto-sync-blog\">自动化同步文章平台（auto-sync-blog）</a>： <a href=\"https://github.com/tea-blog/auto-sync-blog\">https://github.com/tea-blog/auto-sync-blog</a></p>\n<h1>语录</h1>\n<p>南方者，一个热爱计算机更热爱祖国的南方人。</p>\n<h1>更多博客</h1>\n<p><a href=\"https://blog.csdn.net/qq_43263647\">CSDN</a>：<a href=\"https://blog.csdn.net/qq_43263647\">https://blog.csdn.net/qq_43263647</a></p>\n<p><a href=\"https://juejin.cn/user/2840793779295133\">掘金</a>：<a href=\"https://juejin.cn/user/2840793779295133\">https://juejin.cn/user/2840793779295133</a></p>\n<p><a href=\"https://nanfangzhe.cn\">个人网站</a>：<a href=\"https://nanfangzhe.cn\">https://nanfangzhe.cn</a></p>\n",
            "url": "https://clark-cui.top/posts/关于.html",
            "title": "关于",
            "summary": "关于",
            "date_modified": "2023-03-03T00:00:00.000Z",
            "author": {
                "name": "Tea Blog",
                "url": "https://clark-cui.top"
            }
        }
    ]
}